eks_token/__init__.py
eks_token/logics.py
eks_token-0.2.1.dist-info/LICENSE
eks_token-0.2.1.dist-info/METADATA
eks_token-0.2.1.dist-info/WHEEL
eks_token-0.2.1.dist-info/top_level.txt
eks_token-0.2.1.dist-info/RECORD
