Metadata-Version: 2.1
Name: eks_token
Version: 0.2.1
Summary: EKS Token package, an alternate to "aws eks get-token ..." CLI
Home-page: https://github.com/peak-ai/eks-token
Author: Peak AI
Author-email: support@peak.ai
Keywords: eks k8s boto3 awscli python aws
Classifier: Programming Language :: Python :: 3
Classifier: Operating System :: OS Independent
Requires-Python: >=3.6
License-File: LICENSE
Requires-Dist: awscli >=1.27.8
